MANIFEST.in
setup.py
google/__init__.py
google/protobuf/__init__.py
google/protobuf/any_pb2.py
google/protobuf/api_pb2.py
google/protobuf/descriptor.py
google/protobuf/descriptor_database.py
google/protobuf/descriptor_pb2.py
google/protobuf/descriptor_pool.py
google/protobuf/duration_pb2.py
google/protobuf/empty_pb2.py
google/protobuf/field_mask_pb2.py
google/protobuf/json_format.py
google/protobuf/message.py
google/protobuf/message_factory.py
google/protobuf/proto_builder.py
google/protobuf/reflection.py
google/protobuf/service.py
google/protobuf/service_reflection.py
google/protobuf/source_context_pb2.py
google/protobuf/struct_pb2.py
google/protobuf/symbol_database.py
google/protobuf/text_encoding.py
google/protobuf/text_format.py
google/protobuf/timestamp_pb2.py
google/protobuf/type_pb2.py
google/protobuf/wrappers_pb2.py
google/protobuf/compiler/__init__.py
google/protobuf/compiler/plugin_pb2.py
google/protobuf/internal/__init__.py
google/protobuf/internal/_parameterized.py
google/protobuf/internal/api_implementation.py
google/protobuf/internal/containers.py
google/protobuf/internal/decoder.py
google/protobuf/internal/encoder.py
google/protobuf/internal/enum_type_wrapper.py
google/protobuf/internal/message_listener.py
google/protobuf/internal/python_message.py
google/protobuf/internal/type_checkers.py
google/protobuf/internal/wire_format.py
google/protobuf/pyext/__init__.py
google/protobuf/pyext/cpp_message.py
google/protobuf/pyext/python_pb2.py
google/protobuf/util/__init__.py
google/protobuf/util/json_format_proto3_pb2.py
py3_protobuffers.egg-info/PKG-INFO
py3_protobuffers.egg-info/SOURCES.txt
py3_protobuffers.egg-info/dependency_links.txt
py3_protobuffers.egg-info/namespace_packages.txt
py3_protobuffers.egg-info/requires.txt
py3_protobuffers.egg-info/top_level.txt