Metadata-Version: 1.1
Name: py3-protobuffers
Version: 3.0.0a4
Summary: Protocol Buffers
Home-page: https://developers.google.com/protocol-buffers/
Author: protobuf@googlegroups.com
Author-email: protobuf@googlegroups.com
License: New BSD License
Platform: UNKNOWN
Classifier: Programming Language :: Python
Classifier: Programming Language :: Python :: 2
Classifier: Programming Language :: Python :: 2.6
Classifier: Programming Language :: Python :: 2.7
Classifier: Programming Language :: Python :: 3
Classifier: Programming Language :: Python :: 3.3
Classifier: Programming Language :: Python :: 3.4
